keino/__init__.py
keino/add_colourbar.py
keino/build_axes.py
keino/colours.py
keino/copy_artist.py
keino/hash_dict.py
keino/int_path.py
keino/kpath.py
keino/ndindex.py
keino/params.py
keino/pprint_array.py
keino/rounded_polygon.py
keino/vectorize_parallel.py
keino/versioned_import.py
keino-1.0.1.dist-info/licenses/AGPL.txt
keino-1.0.1.dist-info/licenses/GPLv3.txt
keino-1.0.1.dist-info/METADATA
keino-1.0.1.dist-info/WHEEL
keino-1.0.1.dist-info/top_level.txt
keino-1.0.1.dist-info/RECORD
