Metadata-Version: 2.4
Name: keino
Version: 1.0.1
Summary: Useful tools and utilities I use for scientific programming
Author-email: Dan Crawford <daniel.j.crawford@jyu.fi>
License-Expression: GPL-3.0-or-later
Project-URL: Homepage, https://git.sr.ht/~dcrawford/keino
Classifier: Development Status :: 5 - Production/Stable
Classifier: Programming Language :: Python :: 3
Classifier: Topic :: Scientific/Engineering :: Physics
Requires-Python: <3.14,>=3.8
License-File: GPLv3.txt
License-File: AGPL.txt
Requires-Dist: scipy<1.17,>=1.6.0
Requires-Dist: numpy<2.4,>=1.19.0
Dynamic: license-file
